_version.py
ctmd5-0.1.2.dist-info/METADATA
ctmd5-0.1.2.dist-info/WHEEL
ctmd5-0.1.2.dist-info/entry_points.txt
ctmd5-0.1.2.dist-info/licenses/LICENSE
ctmd5.py
ctmd5-0.1.2.dist-info/RECORD
