Metadata-Version: 2.1
Name: ctmd5
Version: 0.1.2
Summary: change the MD5
Keywords: MD5
Author-Email: shkey <shkey325@gmail.com>
License: MIT
Classifier: License :: OSI Approved :: MIT License
Classifier: Programming Language :: Python :: 3
Classifier: Programming Language :: Python :: 3.10
Classifier: Programming Language :: Python :: 3.11
Classifier: Programming Language :: Python :: 3.8
Classifier: Programming Language :: Python :: 3.9
Project-URL: Homepage, https://github.com/shkey/change-the-md5
Requires-Python: >=3.8
Requires-Dist: click>=6.7
